{
  "mealId": "indonesian",
  "n": 80,
  "ayahCount": 42,
  "ayahs": [
    {
      "n": 1,
      "tr": "Dia (Muhammad) bermuka masam dan berpaling,"
    },
    {
      "n": 2,
      "tr": "karena telah datang seorang buta kepadanya."
    },
    {
      "n": 3,
      "tr": "Tahukah kamu barangkali ia ingin membersihkan dirinya (dari dosa),"
    },
    {
      "n": 4,
      "tr": "atau dia (ingin) mendapatkan pengajaran, lalu pengajaran itu memberi manfaat kepadanya?"
    },
    {
      "n": 5,
      "tr": "Adapun orang yang merasa dirinya serba cukup,"
    },
    {
      "n": 6,
      "tr": "maka kamu melayaninya."
    },
    {
      "n": 7,
      "tr": "Padahal tidak ada (celaan) atasmu kalau dia tidak membersihkan diri (beriman)."
    },
    {
      "n": 8,
      "tr": "Dan adapun orang yang datang kepadamu dengan bersegera (untuk mendapatkan pengajaran),"
    },
    {
      "n": 9,
      "tr": "sedang ia takut kepada (Allah),"
    },
    {
      "n": 10,
      "tr": "maka kamu mengabaikannya."
    },
    {
      "n": 11,
      "tr": "Sekali-kali jangan (demikian)! Sesungguhnya ajaran-ajaran Tuhan itu adalah suatu peringatan,"
    },
    {
      "n": 12,
      "tr": "maka barangsiapa yang menghendaki, tentulah ia memperhatikannya,"
    },
    {
      "n": 13,
      "tr": "di dalam kitab-kitab yang dimuliakan,"
    },
    {
      "n": 14,
      "tr": "yang ditinggikan lagi disucikan,"
    },
    {
      "n": 15,
      "tr": "di tangan para penulis (malaikat),"
    },
    {
      "n": 16,
      "tr": "yang mulia lagi berbakti."
    },
    {
      "n": 17,
      "tr": "Binasalah manusia; alangkah amat sangat kekafirannya?"
    },
    {
      "n": 18,
      "tr": "Dari apakah Allah menciptakannya?"
    },
    {
      "n": 19,
      "tr": "Dari setetes mani, Allah menciptakannya lalu menentukannya."
    },
    {
      "n": 20,
      "tr": "Kemudian Dia memudahkan jalannya."
    },
    {
      "n": 21,
      "tr": "kemudian Dia mematikannya dan memasukkannya ke dalam kubur,"
    },
    {
      "n": 22,
      "tr": "kemudian bila Dia menghendaki, Dia membangkitkannya kembali."
    },
    {
      "n": 23,
      "tr": "Sekali-kali jangan; manusia itu belum melaksanakan apa yang diperintahkan Allah kepadanya,"
    },
    {
      "n": 24,
      "tr": "maka hendaklah manusia itu memperhatikan makanannya."
    },
    {
      "n": 25,
      "tr": "Sesungguhnya Kami benar-benar telah mencurahkan air (dari langit),"
    },
    {
      "n": 26,
      "tr": "kemudian Kami belah bumi dengan sebaik-baiknya,"
    },
    {
      "n": 27,
      "tr": "lalu Kami tumbuhkan biji-bijian di bumi itu,"
    },
    {
      "n": 28,
      "tr": "anggur dan sayur-sayuran,"
    },
    {
      "n": 29,
      "tr": "zaitun dan kurma,"
    },
    {
      "n": 30,
      "tr": "kebun-kebun (yang) lebat,"
    },
    {
      "n": 31,
      "tr": "dan buah-buahan serta rumput-rumputan,"
    },
    {
      "n": 32,
      "tr": "untuk kesenanganmu dan untuk binatang-binatang ternakmu."
    },
    {
      "n": 33,
      "tr": "Dan apabila datang suara yang memekakkan (tiupan sangkakala yang kedua),"
    },
    {
      "n": 34,
      "tr": "pada hari ketika manusia lari dari saudaranya,"
    },
    {
      "n": 35,
      "tr": "dari ibu dan bapaknya,"
    },
    {
      "n": 36,
      "tr": "dari istri dan anak-anaknya."
    },
    {
      "n": 37,
      "tr": "Setiap orang dari mereka pada hari itu mempunyai urusan yang cukup menyibukkannya."
    },
    {
      "n": 38,
      "tr": "Banyak muka pada hari itu berseri-seri,"
    },
    {
      "n": 39,
      "tr": "tertawa dan bergembira ria,"
    },
    {
      "n": 40,
      "tr": "dan banyak (pula) muka pada hari itu tertutup debu,"
    },
    {
      "n": 41,
      "tr": "dan ditutup lagi oleh kegelapan."
    },
    {
      "n": 42,
      "tr": "Mereka itulah orang-orang kafir lagi durhaka."
    }
  ]
}
