{
  "mealId": "indonesian",
  "n": 95,
  "ayahCount": 8,
  "ayahs": [
    {
      "n": 1,
      "tr": "Demi (buah) Tin dan (buah) Zaitun,"
    },
    {
      "n": 2,
      "tr": "dan demi bukit Sinai,"
    },
    {
      "n": 3,
      "tr": "dan demi kota (Mekah) ini yang aman,"
    },
    {
      "n": 4,
      "tr": "sesungguhnya Kami telah menciptakan manusia dalam bentuk yang sebaik-baiknya."
    },
    {
      "n": 5,
      "tr": "Kemudian Kami kembalikan dia ke tempat yang serendah-rendahnya (neraka),"
    },
    {
      "n": 6,
      "tr": "kecuali orang-orang yang beriman dan mengerjakan amal saleh; maka bagi mereka pahala yang tiada putus-putusnya."
    },
    {
      "n": 7,
      "tr": "Maka apakah yang menyebabkan kamu mendustakan (hari) pembalasan sesudah (adanya keterangan-keterangan) itu?"
    },
    {
      "n": 8,
      "tr": "Bukankah Allah Hakim yang seadil-adilnya?"
    }
  ]
}
