{
  "mealId": "ahmedali",
  "n": 52,
  "ayahCount": 49,
  "ayahs": [
    {
      "n": 1,
      "tr": "قسم ہے طور کی"
    },
    {
      "n": 2,
      "tr": "اور اس کتاب کی جو لکھی گئی ہے"
    },
    {
      "n": 3,
      "tr": "کشادہ ورقوں میں"
    },
    {
      "n": 4,
      "tr": "اور آباد گھر کی قسم ہے"
    },
    {
      "n": 5,
      "tr": "اور اونچی چھت کی"
    },
    {
      "n": 6,
      "tr": "اور جوش مارتے ہوئے سمندر کی"
    },
    {
      "n": 7,
      "tr": "بے شک آپ کے رب کا عذاب واقع ہوکر رہے گا"
    },
    {
      "n": 8,
      "tr": "اسے کوئی ٹالنے والا نہیں ہے"
    },
    {
      "n": 9,
      "tr": "جس دن آسمان تھرتھرا کر لرزنے لگے گا"
    },
    {
      "n": 10,
      "tr": "اور پہاڑ تیزی سے چلنے لگیں گے"
    },
    {
      "n": 11,
      "tr": "پس اس دن جھٹلانے والوں کے لیے ہلاکت ہے"
    },
    {
      "n": 12,
      "tr": "جو جھوٹی باتوں میں لگے ہوئے کھیل رہے ہیں"
    },
    {
      "n": 13,
      "tr": "جس دن وہ دوزخ کی آگ کی طرف بری طرح سے دھکیلے جائیں گے"
    },
    {
      "n": 14,
      "tr": "یہی وہ آگ ہے جسے تم دنیا میں جھٹلاتے تھے"
    },
    {
      "n": 15,
      "tr": "پس کیایہ جادو ہے یا تم دیکھتے نہیں"
    },
    {
      "n": 16,
      "tr": "اس میں داخل ہو جاؤ پس تم صبر کرو یا نہ کرو تم پر برابر ہے تمہیں تو ویسا ہی بدلہ دیا جائے گا جیسا تم کرتے تھے"
    },
    {
      "n": 17,
      "tr": "بے شک پرہیز گار باغوں اور نعمتوں میں ہوں گے"
    },
    {
      "n": 18,
      "tr": "محظوظ ہو رہے ہوں گے اس سے جو انہیں ان کے رب نے عطا کی ہے اور ان کو ان کے رب نے عذاب دوزخ سے بچا دیا ہے"
    },
    {
      "n": 19,
      "tr": "مزے سے کھاؤ اور پیو بدلے ان (اعمال) کے جو تم کیا کرتے تھے"
    },
    {
      "n": 20,
      "tr": "تختوں پر تکیہ لگائے ہوئے جو قطاروں میں بچھے ہوئے ہیں اور ہم ان کا نکاح بڑی بڑی آنکھوں والی حوروں سے کر دیں گے"
    },
    {
      "n": 21,
      "tr": "اور جو لوگ ایمان لائے اور ان کی اولاد نے ایمان میں ان کی پیروی کی ہم ان کے ساتھ ان کی اولاد کو بھی (جنت) میں ملا دیں گے اور ان کے عمل میں سے کچھ بھی کم نہ کریں گے ہر شخص اپنے عمل کے ساتھ وابستہ ہے"
    },
    {
      "n": 22,
      "tr": "اور ہم انہیں اور زیادہ میوے دیں گے اور گوشت جو وہ چاہیں گے"
    },
    {
      "n": 23,
      "tr": "وہاں ایک دوسرے سے شراب کا پیالہ لیں گے جس میں نہ بکواس ہو گی نہ گناہ کا کام"
    },
    {
      "n": 24,
      "tr": "اور ان کے پاس لڑکے ان کی خدمت کے لیے پھر رہے ہوں گے گویا وہ غلافوں میں رکھے ہوئے موتی ہیں"
    },
    {
      "n": 25,
      "tr": "اور ایک دوسرے کی طرف متوجہ ہو کر آپس میں پوچھیں گے"
    },
    {
      "n": 26,
      "tr": "کہیں گے ہم تو اس سے پہلے اپنے گھروں میں ڈرا کرتے تھے"
    },
    {
      "n": 27,
      "tr": "پس الله نے ہم پر احسان کیا اور ہمیں لُو کے عذاب سے بچا لیا"
    },
    {
      "n": 28,
      "tr": "بے شک ہم اس سے پہلے اسے پکارا کرتے تھے بے شک وہ بڑا ہی احسان کرنے والا نہایت رحم والا ہے"
    },
    {
      "n": 29,
      "tr": "پس نصیحت کرتے رہئے آپ اپنے رب کے فضل سے نہ کاہن ہیں نہ دیوانہ ہیں"
    },
    {
      "n": 30,
      "tr": "کیا وہ کہتے ہیں کہ وہ شاعر ہے ہم اس پر گردشِ زمانہ کا انتظار کر رہے ہیں"
    },
    {
      "n": 31,
      "tr": "کہہ دو تم انتظار کرتے رہو بے شک میں بھی تمہارے ساتھ منتظر ہوں"
    },
    {
      "n": 32,
      "tr": "کیا ان کی عقلیں انہیں اس بات کا حکم دیتی ہیں یا وہ خود ہی سرکش ہیں"
    },
    {
      "n": 33,
      "tr": "یا وہ کہتے ہیں کہ اس نے اسے خود بنا لیا ہے بلکہ وہ ایمان ہی نہیں لاتے"
    },
    {
      "n": 34,
      "tr": "پس کوئی کلام اس جیسا لے آئيں اگر وہ سچے ہیں"
    },
    {
      "n": 35,
      "tr": "کیا وہ بغیر کسی خالق کے پیدا ہو گئے ہیں یا وہ خود خالق ہیں"
    },
    {
      "n": 36,
      "tr": "یا انہوں نے آسمانوں اور زمین کوبنایا ہے نہیں بلکہ وہ یقین ہی نہیں کرتے"
    },
    {
      "n": 37,
      "tr": "کیا ان کے پاس آپ کے رب کے خزانے ہیں یا وہ داروغہ ہیں"
    },
    {
      "n": 38,
      "tr": "کیا ان کے پاس کوئی سیڑھی ہے کہ وہ اس پر چڑھ کر سن آتے ہیں تو لے آئے ان میں سے سننے والا کوئی دلیل واضح"
    },
    {
      "n": 39,
      "tr": "کیا اس کے لیے توبیٹیاں ہیں اور تمہارے لیے بیٹے"
    },
    {
      "n": 40,
      "tr": "کیا آپ ان سے کوئی صلہ مانگتے ہیں کہ وہ تاوان سے دبے جا رہے ہیں"
    },
    {
      "n": 41,
      "tr": "یا ان کے پاس علم غیب ہے کہ وہ اسے لکھتے رہتے ہیں"
    },
    {
      "n": 42,
      "tr": "کیا وہ کوئی داؤ کرنا چاہتے ہیں پس جو منکر ہیں وہی داؤ میں آئے ہوئے ہیں"
    },
    {
      "n": 43,
      "tr": "کیا سوائے الله کے ان کا کوئی اور معبود ہے الله اس سےپاک ہے جو وہ شریک ٹھہراتے ہیں"
    },
    {
      "n": 44,
      "tr": "اگر وہ ایک ٹکڑا آسمان سے گرتا ہوا دیکھ لیں تو کہہ دیں کہ تہ بہ تہ جما ہوا بادل ہے"
    },
    {
      "n": 45,
      "tr": "پس آپ انہیں چھوڑ دیجیئے یہاں تک کہ وہ اپنا وہ دن دیکھ لیں جس میں وہ بے ہوش ہو کر گر پڑیں گے"
    },
    {
      "n": 46,
      "tr": "جس دن ان کا داؤ ان کے کچھ بھی کام نہ آئے گا اور نہ انہیں مدد دی جائے گی"
    },
    {
      "n": 47,
      "tr": "اور بے شک ان ظالموں کو علاوہ اس کے ایک عذاب (دنیا میں) ہوگا لیکن اکثر ان میں سے نہیں جانتے"
    },
    {
      "n": 48,
      "tr": "اور اپنے رب کا حکم آنے تک صبر کر کیوں کہ بےشک آپ ہماری آنکھوں کے سامنے ہیں اور اپنے رب کی حمد کے ساتھ تسبیح کیجیئے جب آپ اٹھا کریں"
    },
    {
      "n": 49,
      "tr": "اور (کچھ حصہ رات میں بھی) اس کی تسبیح کیا کیجیئے اور ستاروں کے غروب ہونے کے بعد بھی"
    }
  ]
}
